EclipsingBinaries/IRAF_Reduction.py
EclipsingBinaries/Night_Filters.py
EclipsingBinaries/OC_plot.py
EclipsingBinaries/OConnell.py
EclipsingBinaries/__init__.py
EclipsingBinaries/apass.py
EclipsingBinaries/color_light_curve.py
EclipsingBinaries/find_min.py
EclipsingBinaries/gaia.py
EclipsingBinaries/menu.py
EclipsingBinaries/multi_aperture_photometry.py
EclipsingBinaries/pipeline.py
EclipsingBinaries/tess_ccd_info.txt
EclipsingBinaries/tess_data_search.py
EclipsingBinaries/tesscut.py
EclipsingBinaries/vseq_updated.py
EclipsingBinaries/examples/APASS_Catalog_ex.txt
EclipsingBinaries/examples/Gaia_output.txt
EclipsingBinaries/examples/O-C_paper_table.txt
EclipsingBinaries/examples/OConnell_plot.png
EclipsingBinaries/examples/OConnell_table.txt
EclipsingBinaries/examples/O_C_ex.png
EclipsingBinaries/examples/__init__.py
EclipsingBinaries/examples/color_light_curve_ex.png
EclipsingBinaries/examples/example_OC_table.txt
EclipsingBinaries/examples/example_regression.txt
EclipsingBinaries/examples/gui_color_light.png
EclipsingBinaries/examples/light_curve_ex.png
EclipsingBinaries/examples/min_program_demo.png
EclipsingBinaries/examples/overlay_example.png
EclipsingBinaries/examples/test_B.txt
EclipsingBinaries/examples/test_R.txt
EclipsingBinaries/examples/test_V.txt
EclipsingBinaries/examples/test_minimums.txt
EclipsingBinaries/examples/calibration_images/purpose.txt
EclipsingBinaries/tests/__init__.py
EclipsingBinaries/tests/test_IRAF_Reduction.py
EclipsingBinaries/tests/test_OC_plot.py
EclipsingBinaries/tests/test_apass.py
docs/EB.rst
docs/__init__.py
docs/changelog.rst
docs/conf.py
docs/contributing.rst
docs/index.rst
docs/installation.rst
docs/license.rst
docs/pipeline.rst
docs/toolbox.rst
docs/_templates/autosummary/base.rst
docs/_templates/autosummary/class.rst
docs/_templates/autosummary/module.rst
EclipsingBinaries-4.1.4.dist-info/LICENSE
EclipsingBinaries-4.1.4.dist-info/METADATA
EclipsingBinaries-4.1.4.dist-info/WHEEL
EclipsingBinaries-4.1.4.dist-info/entry_points.txt
EclipsingBinaries-4.1.4.dist-info/top_level.txt
EclipsingBinaries-4.1.4.dist-info/RECORD
