Metadata-Version: 2.1
Name: EclipsingBinaries
Version: 4.1.4
Summary: "Binary Star Package for Ball State University's Astronomy Research Group"
Home-page: https://eclipsingbinaries.readthedocs.io/
Author: Kyle Koeller
License: MIT
Requires-Python: >=3.8
License-File: LICENSE
Requires-Dist: astropy >=5.2.2
Requires-Dist: astroquery >=0.4.6
Requires-Dist: ccdproc >=2.4.0
Requires-Dist: matplotlib >=3.5.1
Requires-Dist: numpy >=1.22.3
Requires-Dist: pandas >=1.4.2
Requires-Dist: PyAstronomy >=0.18.1
Requires-Dist: scipy >=1.9.3
Requires-Dist: statsmodels >=0.13.5
Requires-Dist: tqdm >=4.64.1
Requires-Dist: numba >=0.57.0
Requires-Dist: seaborn >=0.12.2
Requires-Dist: pyia <=1.41
Requires-Dist: photutils >=1.8.0
Requires-Dist: sphinx >=5
Provides-Extra: docs
Requires-Dist: sphinx-astropy ; extra == 'docs'
Requires-Dist: matplotlib ; extra == 'docs'
